Metadata-Version: 2.1
Name: quickrice
Version: 1.0.3
Summary: A simple CLI tool to manage your desktop themes.
Home-page: https://github.com/halsschmerzen/quickrice
Author: halsschmerzen
Author-email: bastiansteampl@gmail.com
License: MIT
Classifier: License :: OSI Approved :: MIT License
Classifier: Programming Language :: Python :: 3
Classifier: Operating System :: OS Independent
Requires-Python: >=3.6
License-File: LICENSE
